{
    "users":
    [
        {
            "FirstName": "John",
            "LastName": "Smith",
            "EmailAddress": "john.smith@email.net",
            "Password": "Banana55"
        },
        {
            "FirstName": "Jane",
            "LastName": "Smoth",
            "EmailAddress": "jane.smoth@email.net",
            "Password": "Pineapple25"
        },
        {
            "FirstName": "Bruce",
            "LastName": "Wayne",
            "EmailAddress": "bman@batcave.net",
            "Password": "Nightstalker55"
        },
        {
            "FirstName": "Amy",
            "LastName": "Shaftoe",
            "EmailAddress": "america_shaftoe@cryptonomicon.net",
            "Password": "Nightstalker55"
        }
    ]
}